event_schema/__init__.py
event_schema/base.py
event_schema/auth/__init__.py
event_schema/auth/user_login.py
event_schema_profcomff-2024.8.4.dist-info/LICENSE
event_schema_profcomff-2024.8.4.dist-info/METADATA
event_schema_profcomff-2024.8.4.dist-info/WHEEL
event_schema_profcomff-2024.8.4.dist-info/top_level.txt
event_schema_profcomff-2024.8.4.dist-info/RECORD
