Metadata-Version: 2.1
Name: event_schema_profcomff
Version: 2024.8.4
Home-page: https://github.com/profcomff/event-schema
Author: Semyon Grigoriev
Classifier: Programming Language :: Python :: 3.11
License-File: LICENSE
Requires-Dist: pydantic
Requires-Dist: setuptools
